cellmean/__init__.py
cellmean/apply_fill.py
cellmean/dataset.py
cellmean/img_save.py
cellmean/kcell.py
cellmean/plotting.py
cellmean/prep.py
cellmean/saving.py
cellmean/training.py
cellmean/visualise.py
cellmean-1.2.2.dist-info/METADATA
cellmean-1.2.2.dist-info/WHEEL
cellmean-1.2.2.dist-info/top_level.txt
cellmean-1.2.2.dist-info/RECORD
