Metadata-Version: 2.1
Name: cellmean
Version: 1.2.2
Author: TAWSIF AHMED
Author-email: sleeping4cat@outlook.com
Requires-Dist: scikit-learn
Requires-Dist: scikit-image
Requires-Dist: matplotlib
Requires-Dist: pillow
Requires-Dist: mahotas
